MANIFEST.in
README.txt
VERSION.txt
setup.cfg
setup.py
tox.ini
bbcu.bioutils.egg-info/PKG-INFO
bbcu.bioutils.egg-info/SOURCES.txt
bbcu.bioutils.egg-info/dependency_links.txt
bbcu.bioutils.egg-info/requires.txt
bbcu.bioutils.egg-info/top_level.txt
bioutils/__init__.py
bioutils/logging_conf.py
bioutils/barcodes/__init__.py
bioutils/barcodes/demultiplexing.py
bioutils/fastqc/__init__.py
bioutils/fastqc/data.py
bioutils/fastqc/fastqcSummary.py
bioutils/fastqc/io.py
bioutils/pacbio/__init__.py
bioutils/pacbio/primary_files.py
bioutils/pacbio/settings.py
bioutils/seqio/__init__.py
bioutils/seqio/fasta.py
bioutils/tax_db/__init__.py
bioutils/tax_db/db_session.py
bioutils/tax_db/settings.py
bioutils/tax_db/tables.py
scripts/build-taxonomy-db.py
scripts/create-samples-csv.py
scripts/demultiplexing-fastq.py
scripts/gi2name.py
scripts/pacbio-run-status.py