Metadata-Version: 1.0
Name: bbcu.bioutils
Version: 1.0.6
Summary: Common code shared among in-house Bioinformatics python packages
Home-page: UNKNOWN
Author: UNKNOWN
Author-email: UNKNOWN
License: UNKNOWN
Platform: UNKNOWN
